zhujiangyu/__init__.py
zhujiangyu/least_squares.py
zhujiangyu/probability_statistics.py
zhujiangyu/least_squares/__init__.py
zhujiangyu/least_squares/least_squares.py
zhujiangyu/probability_statistics/__init__.py
zhujiangyu/probability_statistics/probability_statistics.py
zhujiangyu-0.2.4.dist-info/LICENSE.txt
zhujiangyu-0.2.4.dist-info/METADATA
zhujiangyu-0.2.4.dist-info/WHEEL
zhujiangyu-0.2.4.dist-info/top_level.txt
zhujiangyu-0.2.4.dist-info/RECORD
