Metadata-Version: 2.1
Name: zhujiangyu
Version: 0.2.4
Summary: 一个好玩的库.
Home-page: https://github.com/Pythonlover2020/zhujangyu
Author: 朱江宇
Author-email: zhuhaibo8@163.com
License: MIT
Platform: UNKNOWN
Classifier: License :: OSI Approved :: MIT License
Classifier: Programming Language :: Python
Classifier: Programming Language :: Python :: 3
Classifier: Programming Language :: Python :: 3.6
Classifier: Programming Language :: Python :: Implementation :: CPython
Classifier: Programming Language :: Python :: Implementation :: PyPy
Requires-Python: >=3.5.0
Requires-Dist: numpy
Requires-Dist: matplotlib
Requires-Dist: sympy
